{
    "assignee": null, 
    "assignees": [], 
    "body": "sending commits range to branch 4.10\n", 
    "closed_at": "2011-08-11T15:12:50Z", 
    "closed_by": {
        "avatar_url": "https://avatars.githubusercontent.com/u/46155?v=3", 
        "events_url": "https://api.github.com/users/dsaff/events{/privacy}", 
        "followers_url": "https://api.github.com/users/dsaff/followers", 
        "following_url": "https://api.github.com/users/dsaff/following{/other_user}", 
        "gists_url": "https://api.github.com/users/dsaff/gists{/gist_id}", 
        "gravatar_id": "", 
        "html_url": "https://github.com/dsaff", 
        "id": 46155, 
        "login": "dsaff", 
        "organizations_url": "https://api.github.com/users/dsaff/orgs", 
        "received_events_url": "https://api.github.com/users/dsaff/received_events", 
        "repos_url": "https://api.github.com/users/dsaff/repos", 
        "site_admin": false, 
        "starred_url": "https://api.github.com/users/dsaff/starred{/owner}{/repo}", 
        "subscriptions_url": "https://api.github.com/users/dsaff/subscriptions", 
        "type": "User", 
        "url": "https://api.github.com/users/dsaff"
    }, 
    "comments": 2, 
    "comments_url": "https://api.github.com/repos/junit-team/junit4/issues/283/comments", 
    "created_at": "2011-08-10T22:18:24Z", 
    "events_url": "https://api.github.com/repos/junit-team/junit4/issues/283/events", 
    "html_url": "https://github.com/junit-team/junit4/pull/283", 
    "id": 1383330, 
    "labels": [
        {
            "color": "3b7d2e", 
            "default": false, 
            "id": 62034, 
            "name": "feature", 
            "url": "https://api.github.com/repos/junit-team/junit4/labels/feature"
        }
    ], 
    "labels_url": "https://api.github.com/repos/junit-team/junit4/issues/283/labels{/name}", 
    "locked": false, 
    "milestone": null, 
    "number": 283, 
    "pull_request": {
        "diff_url": "https://github.com/junit-team/junit4/pull/283.diff", 
        "html_url": "https://github.com/junit-team/junit4/pull/283", 
        "patch_url": "https://github.com/junit-team/junit4/pull/283.patch", 
        "url": "https://api.github.com/repos/junit-team/junit4/pulls/283"
    }, 
    "repository_url": "https://api.github.com/repos/junit-team/junit4", 
    "state": "closed", 
    "title": "4.10 - Recursive temp folders", 
    "updated_at": "2014-06-16T09:11:47Z", 
    "url": "https://api.github.com/repos/junit-team/junit4/issues/283", 
    "user": {
        "avatar_url": "https://avatars.githubusercontent.com/u/48021?v=3", 
        "events_url": "https://api.github.com/users/rodolfoliviero/events{/privacy}", 
        "followers_url": "https://api.github.com/users/rodolfoliviero/followers", 
        "following_url": "https://api.github.com/users/rodolfoliviero/following{/other_user}", 
        "gists_url": "https://api.github.com/users/rodolfoliviero/gists{/gist_id}", 
        "gravatar_id": "", 
        "html_url": "https://github.com/rodolfoliviero", 
        "id": 48021, 
        "login": "rodolfoliviero", 
        "organizations_url": "https://api.github.com/users/rodolfoliviero/orgs", 
        "received_events_url": "https://api.github.com/users/rodolfoliviero/received_events", 
        "repos_url": "https://api.github.com/users/rodolfoliviero/repos", 
        "site_admin": false, 
        "starred_url": "https://api.github.com/users/rodolfoliviero/starred{/owner}{/repo}", 
        "subscriptions_url": "https://api.github.com/users/rodolfoliviero/subscriptions", 
        "type": "User", 
        "url": "https://api.github.com/users/rodolfoliviero"
    }
}